drf_extended/__init__.py
drf_extended/models.py
drf_extended/serializers.py
drf_extended/types.py
drf_extended-0.1.dist-info/METADATA
drf_extended-0.1.dist-info/WHEEL
drf_extended-0.1.dist-info/top_level.txt
drf_extended-0.1.dist-info/RECORD
